
{
  "indexes": [
    {
      "collectionGroup": "users",
      "queryScope": "COLLECTION",
      "fields": [
        { "fieldPath": "center", "order": "ASCENDING" },
        { "fieldPath": "course", "order": "ASCENDING" },
        { "fieldPath": "className", "order": "ASCENDING" },
        { "fieldPath": "trophies", "order": "DESCENDING" }
      ]
    },
    {
      "collectionGroup": "users",
      "queryScope": "COLLECTION",
      "fields": [
        { "fieldPath": "center", "order": "ASCENDING" },
        { "fieldPath": "course", "order": "ASCENDING" },
        { "fieldPath": "className", "order": "ASCENDING" },
        { "fieldPath": "streak", "order": "DESCENDING" }
      ]
    },
    {
      "collectionGroup": "notes",
      "queryScope": "COLLECTION_GROUP",
      "fields": [
        { "fieldPath": "isPinned", "order": "DESCENDING" },
        { "fieldPath": "createdAt", "order": "DESCENDING" }
      ]
    }
  ]
}
